naked_sqla/__init__.py
naked_sqla/__version__.py
naked_sqla/exception.py
naked_sqla/py.typed
naked_sqla/view.py
naked_sqla/om/__init__.py
naked_sqla/om/asession.py
naked_sqla/om/bulk_persistent.py
naked_sqla/om/context.py
naked_sqla/om/loading.py
naked_sqla/om/session.py
naked_sqla-0.1.0.dist-info/METADATA
naked_sqla-0.1.0.dist-info/WHEEL
naked_sqla-0.1.0.dist-info/RECORD
