Metadata-Version: 2.3
Name: naked_sqla
Version: 0.1.0
Summary: A simple and lightweight object mapper around SQLAlchemy core.
Project-URL: repository, https://github.com/ManiMozaffar/naked-sqla
Project-URL: Homepage, https://github.com/ManiMozaffar/naked-sqla
Project-URL: Documentation, https://github.com/ManiMozaffar/naked-sqla
Project-URL: Source, https://github.com/ManiMozaffar/naked-sqla
License-Expression: MIT
Requires-Python: >=3.9
Requires-Dist: sqlalchemy>=2.0.0
Requires-Dist: typing-extensions>=4.0
